lodestar/__init__.py
lodestar/cli/__init__.py
lodestar/cli/app.py
lodestar/cli/commands/__init__.py
lodestar/cli/commands/agent.py
lodestar/cli/commands/doctor.py
lodestar/cli/commands/export.py
lodestar/cli/commands/init.py
lodestar/cli/commands/mcp.py
lodestar/cli/commands/msg.py
lodestar/cli/commands/msg.py.backup
lodestar/cli/commands/reset.py
lodestar/cli/commands/status.py
lodestar/cli/commands/task.py
lodestar/cli/formatters/__init__.py
lodestar/cli/formatters/brief_formatter.py
lodestar/cli/formatters/task_formatter.py
lodestar/cli/templates/__init__.py
lodestar/cli/templates/agents_md.py
lodestar/cli/templates/prd_prompt.py
lodestar/core/__init__.py
lodestar/core/task_service.py
lodestar/mcp/__init__.py
lodestar/mcp/notifications.py
lodestar/mcp/output.py
lodestar/mcp/prompts.py
lodestar/mcp/resources.py
lodestar/mcp/server.py
lodestar/mcp/utils.py
lodestar/mcp/validation.py
lodestar/mcp/tools/__init__.py
lodestar/mcp/tools/agent.py
lodestar/mcp/tools/events.py
lodestar/mcp/tools/message.py
lodestar/mcp/tools/repo.py
lodestar/mcp/tools/task.py
lodestar/mcp/tools/task_mutations.py
lodestar/models/__init__.py
lodestar/models/envelope.py
lodestar/models/runtime.py
lodestar/models/spec.py
lodestar/runtime/__init__.py
lodestar/runtime/converters.py
lodestar/runtime/database.py
lodestar/runtime/engine.py
lodestar/runtime/event_types.py
lodestar/runtime/models.py
lodestar/runtime/alembic/env.py
lodestar/runtime/alembic/script.py.mako
lodestar/runtime/alembic/versions/001_initial_schema.py
lodestar/runtime/alembic/versions/002_add_event_fields.py
lodestar/runtime/alembic/versions/003_task_only_messages.py
lodestar/runtime/repositories/__init__.py
lodestar/runtime/repositories/agent_repo.py
lodestar/runtime/repositories/event_repo.py
lodestar/runtime/repositories/lease_repo.py
lodestar/runtime/repositories/message_repo.py
lodestar/spec/__init__.py
lodestar/spec/dag.py
lodestar/spec/loader.py
lodestar/util/__init__.py
lodestar/util/locks.py
lodestar/util/output.py
lodestar_cli-1.0.1.dist-info/METADATA
lodestar_cli-1.0.1.dist-info/WHEEL
lodestar_cli-1.0.1.dist-info/entry_points.txt
lodestar_cli-1.0.1.dist-info/licenses/LICENSE
lodestar_cli-1.0.1.dist-info/RECORD
