Metadata-Version: 2.4
Name: lodestar-cli
Version: 1.0.1
Summary: Agent-native repo orchestration for multi-agent coordination in Git repositories
Project-URL: Homepage, https://github.com/ThomasRohde/lodestar
Project-URL: Documentation, https://github.com/ThomasRohde/lodestar#readme
Project-URL: Repository, https://github.com/ThomasRohde/lodestar.git
Author: Lodestar Team
License-Expression: MIT
License-File: LICENSE
Keywords: agents,ai,cli,coordination,git
Classifier: Development Status :: 5 - Production/Stable
Classifier: Environment :: Console
Classifier: Intended Audience :: Developers
Classifier: License :: OSI Approved :: MIT License
Classifier: Operating System :: OS Independent
Classifier: Programming Language :: Python :: 3
Classifier: Programming Language :: Python :: 3.13
Classifier: Topic :: Software Development :: Libraries :: Python Modules
Classifier: Typing :: Typed
Requires-Python: >=3.13
Requires-Dist: alembic>=1.13.0
Requires-Dist: atomicwrites>=1.4.0
Requires-Dist: portalocker>=2.0.0
Requires-Dist: pydantic>=2.0.0
Requires-Dist: pyyaml>=6.0
Requires-Dist: rich>=13.0.0
Requires-Dist: sqlalchemy>=2.0.0
Requires-Dist: typer>=0.12.0
Provides-Extra: dev
Requires-Dist: mypy>=1.0.0; extra == 'dev'
Requires-Dist: pre-commit>=4.0.0; extra == 'dev'
Requires-Dist: pytest-anyio>=0.0.0; extra == 'dev'
Requires-Dist: pytest-cov>=4.0.0; extra == 'dev'
Requires-Dist: pytest>=8.0.0; extra == 'dev'
Requires-Dist: ruff>=0.8.0; extra == 'dev'
Requires-Dist: types-pyyaml>=6.0.0; extra == 'dev'
Provides-Extra: docs
Requires-Dist: mkdocs-material>=9.5.0; extra == 'docs'
Requires-Dist: mkdocs>=1.6.0; extra == 'docs'
Provides-Extra: mcp
Requires-Dist: mcp>=1.0.0; extra == 'mcp'
